<?xml version="1.0" encoding="UTF-8"?>

<rootTag>
  <Award>
    <AwardTitle>EAPSI: Relative Importance of Microbial and Geochemical Controls on Arsenic Speciation in Hot Springs</AwardTitle>
    <AwardEffectiveDate>06/01/2011</AwardEffectiveDate>
    <AwardExpirationDate>05/31/2012</AwardExpirationDate>
    <AwardAmount>5700</AwardAmount>
    <AwardInstrument>
      <Value>Fellowship</Value>
    </AwardInstrument>
    <Organization>
      <Code>01060200</Code>
      <Directorate>
        <LongName>OFFICE OF THE DIRECTOR</LongName>
      </Directorate>
      <Division>
        <LongName>Office of International and Integrative Activities</LongName>
      </Division>
    </Organization>
    <ProgramOfficer>
      <SignBlockName>Carter Kimsey</SignBlockName>
    </ProgramOfficer>
    <AbstractNarration/>
    <MinAmdLetterDate>05/18/2011</MinAmdLetterDate>
    <MaxAmdLetterDate>05/18/2011</MaxAmdLetterDate>
    <ARRAAmount/>
    <AwardID>1108019</AwardID>
    <Investigator>
      <FirstName>Laura</FirstName>
      <LastName>Webb</LastName>
      <EmailAddress>webbld2@muohio.edu</EmailAddress>
      <StartDate>05/18/2011</StartDate>
      <EndDate/>
      <RoleCode>1</RoleCode>
    </Investigator>
    <Institution>
      <Name>Webb Laura D</Name>
      <CityName>Hamilton</CityName>
      <ZipCode>450116544</ZipCode>
      <PhoneNumber/>
      <StreetAddress/>
      <CountryName>United States</CountryName>
      <StateName>Ohio</StateName>
      <StateCode>OH</StateCode>
    </Institution>
    <ProgramElement>
      <Code>7316</Code>
      <Text>EAPSI</Text>
    </ProgramElement>
  </Award>
</rootTag>
